app/__init__.py
app/main.py
app/ingest/rest_api_pipeline.py
app/utils/__init__.py
app/utils/logging_utils.py
app/utils/spark_utils.py
app/utils/validation_utils.py
poc_project_dl-0.1.0.dist-info/METADATA
poc_project_dl-0.1.0.dist-info/WHEEL
poc_project_dl-0.1.0.dist-info/top_level.txt
poc_project_dl-0.1.0.dist-info/RECORD
