Metadata-Version: 2.4
Name: poc-project-dl
Version: 0.1.0
Summary: dlt pipeline POC
Requires-Python: >=3.12
Requires-Dist: dlt[duckdb,parquet]>=1.11.0
Requires-Dist: pandas>=2.2.3
Requires-Dist: pytest>=8.4.0
